qaes/__init__.py
qaes/encryption.py
qaes-1.1.0.dist-info/WHEEL
qaes-1.1.0.dist-info/METADATA
qaes-1.1.0.dist-info/RECORD
